endoc/__init__.py
endoc/client.py
endoc/document_search.py
endoc/memsum_summary.py
endoc/paginated_search.py
endoc/queries.py
endoc_sdk-0.1.0.dist-info/LICENSE
endoc_sdk-0.1.0.dist-info/METADATA
endoc_sdk-0.1.0.dist-info/WHEEL
endoc_sdk-0.1.0.dist-info/top_level.txt
endoc_sdk-0.1.0.dist-info/RECORD
