Metadata-Version: 2.1
Name: endoc-sdk
Version: 0.1.0
Summary: Endoc SDK: A note-taking app SDK powered by LLMs
Home-page: https://github.com/yourusername/mysdk
Author: Your Name
Author-email: Your Name <your.email@example.com>
License: MIT
Project-URL: Homepage, https://github.com/yourusername/mysdk
Classifier: Programming Language :: Python :: 3
Classifier: License :: OSI Approved :: MIT License
Classifier: Operating System :: OS Independent
Requires-Python: >=3.7
License-File: LICENSE
Requires-Dist: gql[requests]>=3.5.0
